{
  "gitSyncId": "68ba4c6620834840e9ec7159_79f09587-f7b6-47df-861b-c7d00f10c02a",
  "id": "Calendar Mobile_utils.createEvent",
  "pluginId": "js-plugin",
  "pluginType": "JS",
  "unpublishedAction": {
    "actionConfiguration": {
      "encodeParamsToggle": true,
      "jsArguments": [],
      "paginationType": "NONE",
      "timeoutInMillisecond": 10000
    },
    "collectionId": "Calendar Mobile_utils",
    "confirmBeforeExecute": false,
    "datasource": {
      "isAutoGenerated": false,
      "name": "UNUSED_DATASOURCE",
      "pluginId": "js-plugin"
    },
    "dynamicBindingPathList": [
      {
        "key": "body"
      }
    ],
    "fullyQualifiedName": "utils.createEvent",
    "name": "createEvent",
    "pageId": "Calendar Mobile",
    "runBehaviour": "MANUAL",
    "userSetOnLoad": false
  }
}